LICENSE
README.md
setup.py
carrot/__init__.py
carrot/_version.py
carrot/analyses/__init__.py
carrot/analyses/example_serology.py
carrot/cdm/__init__.py
carrot/cdm/decorators.py
carrot/cdm/model.py
carrot/cdm/operations.py
carrot/cdm/classes/__init__.py
carrot/cdm/objects/__init__.py
carrot/cdm/objects/common.py
carrot/cdm/objects/versions/__init__.py
carrot/cdm/objects/versions/v5_3_1/__init__.py
carrot/cdm/objects/versions/v5_3_1/condition_occurrence.py
carrot/cdm/objects/versions/v5_3_1/death.py
carrot/cdm/objects/versions/v5_3_1/drug_exposure.py
carrot/cdm/objects/versions/v5_3_1/measurement.py
carrot/cdm/objects/versions/v5_3_1/observation.py
carrot/cdm/objects/versions/v5_3_1/person.py
carrot/cdm/objects/versions/v5_3_1/procedure_occurrence.py
carrot/cdm/objects/versions/v5_3_1/specimen.py
carrot/cdm/objects/versions/v5_3_1/visit_occurrence.py
carrot/cli/__init__.py
carrot/cli/cli.py
carrot/cli/subcommands/__init__.py
carrot/cli/subcommands/airflow.py
carrot/cli/subcommands/display.py
carrot/cli/subcommands/etl.py
carrot/cli/subcommands/generate.py
carrot/cli/subcommands/get.py
carrot/cli/subcommands/info.py
carrot/cli/subcommands/pseudonymise.py
carrot/cli/subcommands/run.py
carrot/cli/subcommands/search.py
carrot/data/config/omop.json
carrot/data/example/outputs/condition_occurrence.tsv
carrot/data/example/outputs/measurement.tsv
carrot/data/example/outputs/observation.tsv
carrot/data/example/outputs/person.tsv
carrot/data/example/outputs/person_ids.tsv
carrot/data/example/outputs/summary.tsv
carrot/data/example/sample_config/lion_structural_mapping.json
carrot/data/example/sample_input_data/demo.csv
carrot/data/example/sample_input_data/questions.csv
carrot/data/test/automation/example-full.yml
carrot/data/test/automation/example.yml
carrot/data/test/expected_outputs/condition_occurrence.tsv
carrot/data/test/expected_outputs/measurement.tsv
carrot/data/test/expected_outputs/observation.tsv
carrot/data/test/expected_outputs/person.tsv
carrot_cdm_beta.egg-info/PKG-INFO
carrot_cdm_beta.egg-info/SOURCES.txt
carrot_cdm_beta.egg-info/dependency_links.txt
carrot_cdm_beta.egg-info/entry_points.txt
carrot_cdm_beta.egg-info/requires.txt
carrot_cdm_beta.egg-info/top_level.txt