Metadata-Version: 2.1
Name: carrot-cdm-beta
Version: 0.6.86
Summary: Python package for performing mapping of ETL to CDM 
Home-page: https://github.com/HDRUK/CaRROT-CDM
Author: CO-CONNECT Collaboration
Author-email: calmacx@gmail.com
Classifier: Programming Language :: Python :: 3
Classifier: License :: OSI Approved :: MIT License
Classifier: Operating System :: OS Independent
Requires-Python: >=3.6
Provides-Extra: airflow
Provides-Extra: performance
License-File: LICENSE
